basqet/__init__.py
basqet/basqet_client.py
basqet/network_client.py
basqet/types.py
basqet/exceptions/__init__.py
basqet/exceptions/base.py
basqet/exceptions/forbidden.py
basqet/exceptions/not_acceptable.py
basqet/exceptions/not_found.py
basqet/exceptions/server_error.py
basqet/exceptions/service_unavailable.py
basqet/exceptions/switch_errors.py
basqet/exceptions/unauthorized.py
basqet_python-1.0.dist-info/LICENCE
basqet_python-1.0.dist-info/METADATA
basqet_python-1.0.dist-info/WHEEL
basqet_python-1.0.dist-info/top_level.txt
basqet_python-1.0.dist-info/RECORD
