Metadata-Version: 2.1
Name: basqet-python
Version: 1.0
Summary: A python library to consume Basqet API
Author-email: johnsonoye34@gmail.com
License: MIT
Keywords: Basqet python library
Classifier: Development Status :: 4 - Beta
Classifier: Intended Audience :: Developers
Classifier: License :: OSI Approved :: MIT License
Classifier: Programming Language :: Python :: 3
Classifier: Programming Language :: Python :: 3.10
License-File: LICENCE
Requires-Dist: requests
